django_mediumeditor-1.0.0.dist-info/DESCRIPTION.rst
django_mediumeditor-1.0.0.dist-info/METADATA
django_mediumeditor-1.0.0.dist-info/RECORD
django_mediumeditor-1.0.0.dist-info/WHEEL
django_mediumeditor-1.0.0.dist-info/metadata.json
django_mediumeditor-1.0.0.dist-info/top_level.txt
mediumeditor/__init__.py
mediumeditor/admin.py
mediumeditor/apps.py
mediumeditor/conf.py
mediumeditor/tests.py
mediumeditor/views.py
mediumeditor/widgets.py
mediumeditor/static/css/mediumeditor/django-mediumeditor.css
mediumeditor/static/js/mediumeditor/django-mediumeditor.js
