Metadata-Version: 1.1
Name: django-mediumeditor
Version: 1.0.0
Summary: Medium Editor widget for Django
Home-page: https://github.com/g3rd/django-mediumeditor
Author: Chad Shryock
Author-email: chad@aceportfol.io
License: MIT
Platform: any
Classifier: Development Status :: 4 - Beta
Classifier: Environment :: Web Environment
Classifier: Framework :: Django
Classifier: Intended Audience :: Developers
Classifier: Operating System :: OS Independent
Classifier: Programming Language :: Python
Classifier: Topic :: Software Development :: Libraries :: Python Modules
